{
  "timestamp": "2025-06-09T12:05:00.112Z",
  "url": "/api/automation-batch-14/function-134",
  "method": "POST",
  "headers": {
    "host": "localhost:5000",
    "connection": "keep-alive",
    "content-type": "application/json",
    "accept": "*/*",
    "accept-language": "*",
    "sec-fetch-mode": "cors",
    "user-agent": "node",
    "accept-encoding": "gzip, deflate",
    "content-length": "84"
  },
  "body": {
    "automationExecution": true,
    "functionId": 134,
    "timestamp": "2025-06-09T12:05:00.072Z"
  },
  "query": {}
}